jsonsearch/__init__.py
jsonsearch/jsonsearch.py
jsonsearch-0.0.2.dist-info/LICENSE
jsonsearch-0.0.2.dist-info/METADATA
jsonsearch-0.0.2.dist-info/WHEEL
jsonsearch-0.0.2.dist-info/top_level.txt
jsonsearch-0.0.2.dist-info/RECORD
