Metadata-Version: 2.1
Name: jsonsearch
Version: 0.0.2
Summary: JsonSearch is a simple, yet effcient python library for searhing specific elements in json data.
Home-page: https://github.com/sty945/jsonsearch
Author: sty945
Author-email: sutaoyu@yeah.net
License: UNKNOWN
Project-URL: Bug Tracker, https://github.com/sty945/jsonsearch/issues
Platform: UNKNOWN
Classifier: Programming Language :: Python :: 3
Classifier: License :: OSI Approved :: MIT License
Classifier: Operating System :: OS Independent
Requires-Python: >=3.6
Requires-Dist: pytest (<=3.10.1,>=2.8.0)
